{
  "country": "taiwan",
  "last_updated": "2026-04-25T23:44:15Z",
  "stories": [
    {
      "title": "Beijing’s kinship is just abuse",
      "source": "Taipei Times",
      "url": "https://www.taipeitimes.com/News/editorials/archives/2026/04/26/2003856237",
      "published_date": "2026-04-26T00:00:00Z",
      "category": "Diplomacy"
    },
    {
      "title": "Badminton》See you in 3 sets of 21 points! BWF announced that it will change to a 3-inning 15-point system in January 2027",
      "source": "Liberty Times",
      "url": "https://sports.ltn.com.tw/news/breakingnews/5416045",
      "published_date": "2026-04-25T23:17:42Z",
      "category": "Diplomacy"
    },
    {
      "title": "A ruthless father was in debt and sold his wife and abandoned his children. The court exempted 3 children from their child support obligations.",
      "source": "Liberty Times",
      "url": "https://news.ltn.com.tw/news/society/breakingnews/5416047",
      "published_date": "2026-04-25T23:10:04Z",
      "category": "Diplomacy"
    },
    {
      "title": "04/26 List of key news from each newspaper",
      "source": "Liberty Times",
      "url": "https://news.ltn.com.tw/news/life/breakingnews/5416036",
      "published_date": "2026-04-25T22:48:02Z",
      "category": "Diplomacy"
    },
    {
      "title": "The civil engineering bid for the China-Jieqing Blue Line has failed for the second time. The June start date has been delayed. Construction is conservatively estimated to start in August.",
      "source": "Liberty Times",
      "url": "https://news.ltn.com.tw/news/life/breakingnews/5416038",
      "published_date": "2026-04-25T22:47:45Z",
      "category": "Diplomacy"
    },
    {
      "title": "The sun shows its face! The temperature has obviously returned in various places today, and another front will report on Wednesday",
      "source": "Liberty Times",
      "url": "https://news.ltn.com.tw/news/life/breakingnews/5416035",
      "published_date": "2026-04-25T22:45:06Z",
      "category": "Diplomacy"
    },
    {
      "title": "US-Iran talks break down! Trump abruptly withdraws the US delegation and criticizes Tehran for internal infighting and chaos",
      "source": "Liberty Times",
      "url": "https://news.ltn.com.tw/news/world/breakingnews/5416024",
      "published_date": "2026-04-25T22:03:34Z",
      "category": "Diplomacy"
    },
    {
      "title": "Lin Jialong serves as presidential envoy, breaks blockade and arrives in Eswatini",
      "source": "Liberty Times",
      "url": "https://news.ltn.com.tw/news/politics/paper/1752382",
      "published_date": "2026-04-25T21:30:00Z",
      "category": "Diplomacy"
    },
    {
      "title": "China blocks foreign visit, Qiu Chuizheng: exerting maximum pressure on Taiwan",
      "source": "Liberty Times",
      "url": "https://news.ltn.com.tw/news/politics/paper/1752368",
      "published_date": "2026-04-25T21:30:00Z",
      "category": "Diplomacy"
    },
    {
      "title": "Confronting the US, China and Russia’s anti-European stance, Macron calls for unity",
      "source": "Liberty Times",
      "url": "https://news.ltn.com.tw/news/world/paper/1752423",
      "published_date": "2026-04-25T21:30:00Z",
      "category": "Diplomacy"
    },
    {
      "title": "To prevent the \"second\" Li Zhenxiu controversy, the Mainland Affairs Council approves the regulations on allocation of registration in China",
      "source": "Liberty Times",
      "url": "https://news.ltn.com.tw/news/politics/paper/1752366",
      "published_date": "2026-04-25T21:30:00Z",
      "category": "Diplomacy"
    },
    {
      "title": "Lin Jialong meets with King of Eswatini",
      "source": "Liberty Times",
      "url": "https://news.ltn.com.tw/news/politics/paper/1752369",
      "published_date": "2026-04-25T21:30:00Z",
      "category": "Diplomacy"
    },
    {
      "title": "TSMC insider leak case to be sentenced tomorrow",
      "source": "Liberty Times",
      "url": "https://ec.ltn.com.tw/article/paper/1752390",
      "published_date": "2026-04-25T21:30:00Z",
      "category": "Diplomacy"
    },
    {
      "title": "Second round of U.S.-Iran talks undecided, both representatives downgraded",
      "source": "Liberty Times",
      "url": "https://news.ltn.com.tw/news/world/paper/1752424",
      "published_date": "2026-04-25T21:30:00Z",
      "category": "Diplomacy"
    },
    {
      "title": "The second round of talks between the United States and Iran is cancelled! Trump calls it a waste of time: Iran is in chaos",
      "source": "Liberty Times",
      "url": "https://news.ltn.com.tw/news/world/breakingnews/5416023",
      "published_date": "2026-04-25T17:10:48Z",
      "category": "Diplomacy"
    },
    {
      "title": "Trump cancels US-Iran talks, says no need to fly 18 hours for empty talk",
      "source": "Liberty Times",
      "url": "https://news.ltn.com.tw/news/world/breakingnews/5416022",
      "published_date": "2026-04-25T16:54:03Z",
      "category": "Diplomacy"
    },
    {
      "title": "Iran's foreign minister leaves Pakistan, direct talks between US and Iran fail",
      "source": "Liberty Times",
      "url": "https://news.ltn.com.tw/news/world/breakingnews/5416017",
      "published_date": "2026-04-25T16:13:21Z",
      "category": "Diplomacy"
    },
    {
      "title": "Liu Baijun, who was once accused of being a non-communist, angrily said: The presence of Ke Wenzhe in Taiwanese politics is a great harm.",
      "source": "Liberty Times",
      "url": "https://news.ltn.com.tw/news/politics/breakingnews/5416000",
      "published_date": "2026-04-25T15:34:22Z",
      "category": "Diplomacy"
    },
    {
      "title": "U.S. think tanks say arms purchases cannot be made by the Republic of China and become \"negative assets\". The blue committee refutes them on the spot",
      "source": "Liberty Times",
      "url": "https://news.ltn.com.tw/news/politics/breakingnews/5415997",
      "published_date": "2026-04-25T15:11:07Z",
      "category": "Diplomacy"
    },
    {
      "title": "Are you suspended from NATO for refusing to support the war in Iraq? Spanish Prime Minister: Not worried at all",
      "source": "Liberty Times",
      "url": "https://news.ltn.com.tw/news/world/breakingnews/5415984",
      "published_date": "2026-04-25T14:41:46Z",
      "category": "Diplomacy"
    },
    {
      "title": "President Lai outlines medical subsidy plans",
      "source": "Taipei Times",
      "url": "https://www.taipeitimes.com/News/front/archives/2026/04/26/2003856246",
      "published_date": "2026-04-26T00:00:00Z",
      "category": "Military"
    },
    {
      "title": "Labor ministry defends plan for Indian workers",
      "source": "Taipei Times",
      "url": "https://www.taipeitimes.com/News/taiwan/archives/2026/04/26/2003856255",
      "published_date": "2026-04-26T00:00:00Z",
      "category": "Military"
    },
    {
      "title": "Soldier sentenced for sleeping at guard post",
      "source": "Taipei Times",
      "url": "https://www.taipeitimes.com/News/taiwan/archives/2026/04/26/2003856257",
      "published_date": "2026-04-26T00:00:00Z",
      "category": "Military"
    },
    {
      "title": "Military concludes 14-day Han Kuang drills",
      "source": "Taipei Times",
      "url": "https://www.taipeitimes.com/News/taiwan/archives/2026/04/26/2003856265",
      "published_date": "2026-04-26T00:00:00Z",
      "category": "Military"
    },
    {
      "title": "Harry's love affair has made great progress! The woman wears a diamond ring and is rumored to be engaged after 8 months of dating.",
      "source": "Liberty Times",
      "url": "https://ent.ltn.com.tw/news/breakingnews/5416048",
      "published_date": "2026-04-25T23:23:22Z",
      "category": "Military"
    },
    {
      "title": "NBA Playoffs》SGA's shooting percentage exceeded 80%, and he scored 42 points. Thunder series draws",
      "source": "Liberty Times",
      "url": "https://sports.ltn.com.tw/news/breakingnews/5416039",
      "published_date": "2026-04-25T23:16:08Z",
      "category": "Military"
    },
    {
      "title": "NBA Playoffs\" The Eighth Legend? The Magic beat the top-seeded Pistons again and took a 2:1 lead in the series.",
      "source": "Liberty Times",
      "url": "https://sports.ltn.com.tw/news/breakingnews/5416037",
      "published_date": "2026-04-25T23:15:04Z",
      "category": "Military"
    },
    {
      "title": "Wang Liren’s SWAG live broadcast attracted 5,000 pilgrims! \"Lifting Clothes and Being Seen\" Plus Code to Unlock Personal Massage",
      "source": "Liberty Times",
      "url": "https://ent.ltn.com.tw/news/breakingnews/5416008",
      "published_date": "2026-04-25T23:03:31Z",
      "category": "Military"
    },
    {
      "title": "\"Two Dads\" Wendy grows up and becomes super beautiful! Close to the male idol on campus... pink bubbles overflow",
      "source": "Liberty Times",
      "url": "https://ent.ltn.com.tw/news/breakingnews/5416030",
      "published_date": "2026-04-25T23:01:30Z",
      "category": "Military"
    },
    {
      "title": "Magic retreats and Pistons counterattack, leading 2-1 in the Eastern Conference series",
      "source": "Liberty Times",
      "url": "https://sports.ltn.com.tw/news/breakingnews/5416034",
      "published_date": "2026-04-25T21:36:03Z",
      "category": "Military"
    },
    {
      "title": "US, Japan and Philippines conduct side-by-side military drills, Chinese aircraft and warships disrupt Taiwan and Philippines",
      "source": "Liberty Times",
      "url": "https://news.ltn.com.tw/news/politics/paper/1752383",
      "published_date": "2026-04-25T21:30:00Z",
      "category": "Military"
    },
    {
      "title": "Asian Beach Games Wu Ci'en wins bronze in women's shot put",
      "source": "Liberty Times",
      "url": "https://sports.ltn.com.tw/news/paper/1752384",
      "published_date": "2026-04-25T21:30:00Z",
      "category": "Military"
    },
    {
      "title": "Xu Yuren: Arms purchase cannot be completed until May 7 and may be suspended by Trump",
      "source": "Liberty Times",
      "url": "https://news.ltn.com.tw/news/politics/paper/1752372",
      "published_date": "2026-04-25T21:30:00Z",
      "category": "Military"
    },
    {
      "title": "Constructing an unmanned army, the national army plans to introduce robot dogs and unmanned vehicles",
      "source": "Liberty Times",
      "url": "https://news.ltn.com.tw/news/politics/paper/1752370",
      "published_date": "2026-04-25T21:30:00Z",
      "category": "Military"
    },
    {
      "title": "Focus Commentary》The Opposition Party’s Risk of Confession",
      "source": "Liberty Times",
      "url": "https://news.ltn.com.tw/news/politics/paper/1752373",
      "published_date": "2026-04-25T21:30:00Z",
      "category": "Military"
    },
    {
      "title": "If the arms purchase regulations are passed, the Democratic Progressive Party Group: There is still a budget to review, which may delay the Sichuan-Xi meeting",
      "source": "Liberty Times",
      "url": "https://news.ltn.com.tw/news/politics/paper/1752371",
      "published_date": "2026-04-25T21:30:00Z",
      "category": "Military"
    },
    {
      "title": "Ministry of Labor: Japan and the Star introduce Indian workers, but public security has not deteriorated",
      "source": "Liberty Times",
      "url": "https://ec.ltn.com.tw/article/paper/1752374",
      "published_date": "2026-04-25T21:30:00Z",
      "category": "Military"
    },
    {
      "title": "Two waves of baby boomers are taking over and retiring, and 870,000 migrant workers are unable to fill the gap of 5 million.",
      "source": "Liberty Times",
      "url": "https://ec.ltn.com.tw/article/paper/1752377",
      "published_date": "2026-04-25T21:30:00Z",
      "category": "Military"
    },
    {
      "title": "Japan, stars and South Korea have the experience to fill gaps in specific industries and design introduction thresholds",
      "source": "Liberty Times",
      "url": "https://ec.ltn.com.tw/article/paper/1752375",
      "published_date": "2026-04-25T21:30:00Z",
      "category": "Military"
    },
    {
      "title": "Federation of Industry and Commerce: Opponents do not understand industry needs",
      "source": "Liberty Times",
      "url": "https://ec.ltn.com.tw/article/paper/1752378",
      "published_date": "2026-04-25T21:30:00Z",
      "category": "Military"
    },
    {
      "title": "Wild Balkan berries keep gin taste steady as climate shifts",
      "source": "Taipei Times",
      "url": "https://www.taipeitimes.com/News/biz/archives/2026/04/26/2003856235",
      "published_date": "2026-04-26T00:00:00Z",
      "category": "Energy"
    },
    {
      "title": "Firms still lukewarm on climate promises",
      "source": "Taipei Times",
      "url": "https://www.taipeitimes.com/News/editorials/archives/2026/04/26/2003856239",
      "published_date": "2026-04-26T00:00:00Z",
      "category": "Energy"
    },
    {
      "title": "Health Network》Nutritionist reveals the \"3-minute super speed breakfast\" to wake up the brain and no longer \"cut off the power\" at 10 a.m.",
      "source": "Liberty Times",
      "url": "https://health.ltn.com.tw/article/breakingnews/5415948",
      "published_date": "2026-04-25T23:16:00Z",
      "category": "Energy"
    },
    {
      "title": "Oil prices freeze for 4th time in a row, China National Petroleum Corporation absorbs 12.4 billion in total",
      "source": "Liberty Times",
      "url": "https://ec.ltn.com.tw/article/paper/1752391",
      "published_date": "2026-04-25T21:30:00Z",
      "category": "Energy"
    },
    {
      "title": "Weekly Special: Trump’s war with Iran is quietly rewriting China’s script for invading Taiwan",
      "source": "Liberty Times",
      "url": "https://news.ltn.com.tw/news/world/paper/1752392",
      "published_date": "2026-04-25T21:30:00Z",
      "category": "Energy"
    },
    {
      "title": "Strait of Hormuz blocked, U.S. energy exports hit record high",
      "source": "Liberty Times",
      "url": "https://news.ltn.com.tw/news/world/paper/1752426",
      "published_date": "2026-04-25T21:30:00Z",
      "category": "Energy"
    },
    {
      "title": "Trump sanctions work! Oil storage on Khag Island is about to reach its limit, and Iran urgently deploys idle oil tankers as offshore warehouses",
      "source": "Liberty Times",
      "url": "https://news.ltn.com.tw/news/world/breakingnews/5415987",
      "published_date": "2026-04-25T15:03:53Z",
      "category": "Energy"
    },
    {
      "title": "The biggest winner in the Middle East war? U.S. oil exports hit record high of nearly 12.9 million barrels per day",
      "source": "Liberty Times",
      "url": "https://news.ltn.com.tw/news/world/breakingnews/5415936",
      "published_date": "2026-04-25T13:21:17Z",
      "category": "Energy"
    },
    {
      "title": "The Environmental Alliance appeals: Remember the lessons learned from the Chernobyl nuclear disaster 40 years ago and oppose the nuclear restart",
      "source": "Liberty Times",
      "url": "https://news.ltn.com.tw/news/life/breakingnews/5415824",
      "published_date": "2026-04-25T10:24:50Z",
      "category": "Energy"
    },
    {
      "title": "Secondary Vocational School》Field management \"fired home plate\" before the game to save the field. Lotte and Weichuan were still suspended due to rain in the 3rd inning.",
      "source": "Liberty Times",
      "url": "https://sports.ltn.com.tw/news/breakingnews/5415820",
      "published_date": "2026-04-25T10:11:17Z",
      "category": "Energy"
    },
    {
      "title": "China National Petroleum Corporation announced that oil prices will be frozen for four consecutive times next week, with gasoline and diesel absorbing a total of 12.4 billion yuan.",
      "source": "Liberty Times",
      "url": "https://ec.ltn.com.tw/article/breakingnews/5415592",
      "published_date": "2026-04-25T06:21:34Z",
      "category": "Energy"
    },
    {
      "title": "Understanding Citizen Technology 5》The Ministry of Digital Development launches three major strategies to strengthen their application in disaster prevention and response",
      "source": "Liberty Times",
      "url": "https://ec.ltn.com.tw/article/breakingnews/5415542",
      "published_date": "2026-04-25T05:45:58Z",
      "category": "Energy"
    },
    {
      "title": "Taiwan’s ranking revealed! Global oil price rankings released, the gap between countries is astonishing",
      "source": "Liberty Times",
      "url": "https://ec.ltn.com.tw/article/breakingnews/5415433",
      "published_date": "2026-04-25T04:01:08Z",
      "category": "Energy"
    },
    {
      "title": "Before the Trump-Xi meeting... The United States imposes sanctions on Chinese oil refining giants and dozens of shipping companies, cutting off Iran’s gold veins",
      "source": "Liberty Times",
      "url": "https://news.ltn.com.tw/news/world/breakingnews/5415234",
      "published_date": "2026-04-25T00:05:00Z",
      "category": "Energy"
    },
    {
      "title": "Taiwan to secure energy soft spots",
      "source": "Taipei Times",
      "url": "https://www.taipeitimes.com/News/editorials/archives/2026/04/25/2003856194",
      "published_date": "2026-04-25T00:00:00Z",
      "category": "Energy"
    },
    {
      "title": "Last-gasp Tomas stunner sends Stuttgart to final",
      "source": "Taipei Times",
      "url": "https://www.taipeitimes.com/News/sport/archives/2026/04/25/2003856209",
      "published_date": "2026-04-25T00:00:00Z",
      "category": "Energy"
    },
    {
      "title": "Blue and white amend the air pollution law and expand local authority. Federation of Industry and Commerce: Power plants and factories may explode and close down.",
      "source": "Liberty Times",
      "url": "https://ec.ltn.com.tw/article/paper/1752278",
      "published_date": "2026-04-24T21:30:00Z",
      "category": "Energy"
    },
    {
      "title": "The Republican Party's situation in the US midterm elections is not good. Poll: Soaring oil prices and people resent Trump",
      "source": "Liberty Times",
      "url": "https://news.ltn.com.tw/news/world/breakingnews/5415167",
      "published_date": "2026-04-24T15:07:52Z",
      "category": "Energy"
    },
    {
      "title": "\"Hot summer days\" exceeding 40 degrees occur frequently. Tokyo encourages employees to wear shorts to work",
      "source": "Liberty Times",
      "url": "https://news.ltn.com.tw/news/world/breakingnews/5414818",
      "published_date": "2026-04-24T12:06:31Z",
      "category": "Energy"
    },
    {
      "title": "Xingda coal-fired unit No. 4 was criticized for fake testing and actually generated electricity? Taipower: Routine testing, included in annual operating hours",
      "source": "Liberty Times",
      "url": "https://ec.ltn.com.tw/article/breakingnews/5414850",
      "published_date": "2026-04-24T09:21:27Z",
      "category": "Energy"
    },
    {
      "title": "Alaskan village tries to revive its polar bear tourism industry",
      "source": "Taipei Times",
      "url": "https://www.taipeitimes.com/News/biz/archives/2026/04/26/2003856234",
      "published_date": "2026-04-26T00:00:00Z",
      "category": "Economy"
    },
    {
      "title": "Morocco’s new model economy",
      "source": "Taipei Times",
      "url": "https://www.taipeitimes.com/News/editorials/archives/2026/04/26/2003856241",
      "published_date": "2026-04-26T00:00:00Z",
      "category": "Economy"
    },
    {
      "title": "The Haunting of Heirs 2》Inheritance division and foreclosure occurs on average once a day",
      "source": "Liberty Times",
      "url": "https://ec.ltn.com.tw/article/breakingnews/5415475",
      "published_date": "2026-04-25T23:31:00Z",
      "category": "Economy"
    },
    {
      "title": "Popular Groups》Leader MediaTek hits new highs, IC design stocks rush to make AI fortune",
      "source": "Liberty Times",
      "url": "https://ec.ltn.com.tw/article/breakingnews/5414950",
      "published_date": "2026-04-25T23:00:00Z",
      "category": "Economy"
    },
    {
      "title": "You have to worry about cutting vegetables and drying clothes! After fighting for 8 million, I was happy to retire. Abei pointed out the tragedy at home.",
      "source": "Liberty Times",
      "url": "https://ec.ltn.com.tw/article/breakingnews/5415939",
      "published_date": "2026-04-25T22:21:47Z",
      "category": "Economy"
    },
    {
      "title": "Keelung youth unemployment rate is 8%, Tong Ziweiti builds employment safety net",
      "source": "Liberty Times",
      "url": "https://news.ltn.com.tw/news/politics/paper/1752439",
      "published_date": "2026-04-25T21:30:00Z",
      "category": "Economy"
    },
    {
      "title": "Huida's share price hits new high, market value returns to US$5 trillion",
      "source": "Liberty Times",
      "url": "https://ec.ltn.com.tw/article/paper/1752389",
      "published_date": "2026-04-25T21:30:00Z",
      "category": "Economy"
    },
    {
      "title": "Internet restrictions and economic problems have heightened public dissatisfaction. Internet celebrities publicly called out Putin, and loyalists also issued warnings.",
      "source": "Liberty Times",
      "url": "https://news.ltn.com.tw/news/world/breakingnews/5415950",
      "published_date": "2026-04-25T14:23:00Z",
      "category": "Economy"
    },
    {
      "title": "AI cheers! Taiwan’s stock market capitalization is close to that of Canada, TSMC ranks as the sixth largest company in the world",
      "source": "Liberty Times",
      "url": "https://ec.ltn.com.tw/article/breakingnews/5415938",
      "published_date": "2026-04-25T13:29:47Z",
      "category": "Economy"
    },
    {
      "title": "Are there any grandchildren missing? Inheriting an inheritance of 30 million yuan and becoming a rich woman instantly. Grandma swiped her bankbook and shouted, \"How should I spend it?\"",
      "source": "Liberty Times",
      "url": "https://ec.ltn.com.tw/article/breakingnews/5415754",
      "published_date": "2026-04-25T10:57:55Z",
      "category": "Economy"
    },
    {
      "title": "The villagers are on their knees! 7 years ago, the single-pressure TSMC PTT \"god-level\" statement was exposed",
      "source": "Liberty Times",
      "url": "https://news.ltn.com.tw/news/life/breakingnews/5415763",
      "published_date": "2026-04-25T10:54:56Z",
      "category": "Economy"
    },
    {
      "title": "It is difficult to catch up with TSMC with advanced manufacturing processes. Has Intel found a breakthrough point?",
      "source": "Liberty Times",
      "url": "https://ec.ltn.com.tw/article/breakingnews/5415696",
      "published_date": "2026-04-25T08:36:49Z",
      "category": "Economy"
    },
    {
      "title": "Lost contact for more than 10 days... Zhang Junchuan, two-time Olympic champion and chairman of the Chinese Badminton Association, was investigated by the disciplinary inspection department",
      "source": "Liberty Times",
      "url": "https://news.ltn.com.tw/news/world/breakingnews/5415684",
      "published_date": "2026-04-25T08:16:57Z",
      "category": "Economy"
    },
    {
      "title": "TSMC joins the list! Don’t miss it if you pass by. Foreign media revealed 5 AI stocks with huge potential.",
      "source": "Liberty Times",
      "url": "https://ec.ltn.com.tw/article/breakingnews/5415709",
      "published_date": "2026-04-25T08:04:56Z",
      "category": "Economy"
    },
    {
      "title": "Chunyu helped Taiwan’s reservoirs replenish 41.31 million tons of water, and Shimen ranked first in Taiwan’s revenue",
      "source": "Liberty Times",
      "url": "https://ec.ltn.com.tw/article/breakingnews/5415680",
      "published_date": "2026-04-25T07:52:31Z",
      "category": "Economy"
    },
    {
      "title": "Huida has a market value of US$5 trillion, leading the second place by US$1 trillion? No more \"easy money\"?",
      "source": "Liberty Times",
      "url": "https://ec.ltn.com.tw/article/breakingnews/5415564",
      "published_date": "2026-04-25T06:18:01Z",
      "category": "Economy"
    },
    {
      "title": "The cooperation between the two major technology giants deepens! Meta fully introduces AWS chips to enter the AI ​​era",
      "source": "Liberty Times",
      "url": "https://ec.ltn.com.tw/article/breakingnews/5415411",
      "published_date": "2026-04-25T03:48:15Z",
      "category": "Economy"
    },
    {
      "title": "Labor shortage dilemma 2》What industries do Indian migrant workers work in in Japan and South Korea?",
      "source": "Liberty Times",
      "url": "https://ec.ltn.com.tw/article/breakingnews/5415294",
      "published_date": "2026-04-25T03:01:00Z",
      "category": "Economy"
    },
    {
      "title": "980,000 disappeared instantly! He wanted to rely on investment to make a comeback, but he ended up miserable.",
      "source": "Liberty Times",
      "url": "https://ec.ltn.com.tw/article/breakingnews/5415363",
      "published_date": "2026-04-25T03:00:00Z",
      "category": "Economy"
    },
    {
      "title": "Taiwanese retail investors are very good at buying it! Taiwan's stock market value continues to overtake foreign media reveals that \"these companies\" have the strongest confidence",
      "source": "Liberty Times",
      "url": "https://ec.ltn.com.tw/article/breakingnews/5415339",
      "published_date": "2026-04-25T02:24:52Z",
      "category": "Economy"
    },
    {
      "title": "Lin Chia-lung visits Eswatini as envoy",
      "source": "Taipei Times",
      "url": "https://www.taipeitimes.com/News/front/archives/2026/04/26/2003856245",
      "published_date": "2026-04-26T00:00:00Z",
      "category": "Local Events"
    },
    {
      "title": "Care shortage expected as population grows older",
      "source": "Taipei Times",
      "url": "https://www.taipeitimes.com/News/front/archives/2026/04/26/2003856247",
      "published_date": "2026-04-26T00:00:00Z",
      "category": "Local Events"
    },
    {
      "title": "US envoys head to Pakistan for Iran war talks",
      "source": "Taipei Times",
      "url": "https://www.taipeitimes.com/News/front/archives/2026/04/26/2003856248",
      "published_date": "2026-04-26T00:00:00Z",
      "category": "Local Events"
    },
    {
      "title": "Netanyahu says tumor removed from his prostate",
      "source": "Taipei Times",
      "url": "https://www.taipeitimes.com/News/front/archives/2026/04/26/2003856249",
      "published_date": "2026-04-26T00:00:00Z",
      "category": "Local Events"
    },
    {
      "title": "Bus accident in Gansu kills one, injures 12 Taiwanese: SEF",
      "source": "Taipei Times",
      "url": "https://www.taipeitimes.com/News/taiwan/archives/2026/04/26/2003856256",
      "published_date": "2026-04-26T00:00:00Z",
      "category": "Local Events"
    },
    {
      "title": "High-value will declared invalid in inheritance dispute",
      "source": "Taipei Times",
      "url": "https://www.taipeitimes.com/News/taiwan/archives/2026/04/26/2003856258",
      "published_date": "2026-04-26T00:00:00Z",
      "category": "Local Events"
    },
    {
      "title": "Man convicted of robbing student of NT$100 in Hualien",
      "source": "Taipei Times",
      "url": "https://www.taipeitimes.com/News/taiwan/archives/2026/04/26/2003856259",
      "published_date": "2026-04-26T00:00:00Z",
      "category": "Local Events"
    },
    {
      "title": "Man attacks two-year-old at Taipei Main Station",
      "source": "Taipei Times",
      "url": "https://www.taipeitimes.com/News/taiwan/archives/2026/04/26/2003856260",
      "published_date": "2026-04-26T00:00:00Z",
      "category": "Local Events"
    },
    {
      "title": "Thai Festival in Taipei celebrates people-to-people ties",
      "source": "Taipei Times",
      "url": "https://www.taipeitimes.com/News/taiwan/archives/2026/04/26/2003856261",
      "published_date": "2026-04-26T00:00:00Z",
      "category": "Local Events"
    },
    {
      "title": "Foreign lawmakers slam canceled trip",
      "source": "Taipei Times",
      "url": "https://www.taipeitimes.com/News/taiwan/archives/2026/04/26/2003856262",
      "published_date": "2026-04-26T00:00:00Z",
      "category": "Local Events"
    },
    {
      "title": "Taipei rejects Mauritius ‘no flight approval’ claim",
      "source": "Taipei Times",
      "url": "https://www.taipeitimes.com/News/taiwan/archives/2026/04/26/2003856263",
      "published_date": "2026-04-26T00:00:00Z",
      "category": "Local Events"
    },
    {
      "title": "Taiwan fears it will be ‘on menu’ of Trump-Xi meet",
      "source": "Taipei Times",
      "url": "https://www.taipeitimes.com/News/taiwan/archives/2026/04/26/2003856264",
      "published_date": "2026-04-26T00:00:00Z",
      "category": "Local Events"
    },
    {
      "title": "MAC requires renunciation proof for residency process",
      "source": "Taipei Times",
      "url": "https://www.taipeitimes.com/News/taiwan/archives/2026/04/26/2003856266",
      "published_date": "2026-04-26T00:00:00Z",
      "category": "Local Events"
    },
    {
      "title": "The race for DPP Taipei mayor nominee heats up",
      "source": "Taipei Times",
      "url": "https://www.taipeitimes.com/News/taiwan/archives/2026/04/26/2003856267",
      "published_date": "2026-04-26T00:00:00Z",
      "category": "Local Events"
    },
    {
      "title": "School dedicated to Shinzo Abe’s policies opens",
      "source": "Taipei Times",
      "url": "https://www.taipeitimes.com/News/taiwan/archives/2026/04/26/2003856268",
      "published_date": "2026-04-26T00:00:00Z",
      "category": "Local Events"
    },
    {
      "title": "STUF forum spotlights women’s empowerment and Taiwan’s global role",
      "source": "Taipei Times",
      "url": "https://www.taipeitimes.com/News/taiwan/archives/2026/04/26/2003856269",
      "published_date": "2026-04-26T00:00:00Z",
      "category": "Local Events"
    },
    {
      "title": "Traditional parade",
      "source": "Taipei Times",
      "url": "https://www.taipeitimes.com/News/taiwan/archives/2026/04/26/2003856270",
      "published_date": "2026-04-26T00:00:00Z",
      "category": "Local Events"
    },
    {
      "title": "Crowded crossing",
      "source": "Taipei Times",
      "url": "https://www.taipeitimes.com/News/taiwan/archives/2026/04/26/2003856271",
      "published_date": "2026-04-26T00:00:00Z",
      "category": "Local Events"
    },
    {
      "title": "Religious participation",
      "source": "Taipei Times",
      "url": "https://www.taipeitimes.com/News/taiwan/archives/2026/04/26/2003856272",
      "published_date": "2026-04-26T00:00:00Z",
      "category": "Local Events"
    },
    {
      "title": "EDITORIAL: KMT cheering for the wrong team",
      "source": "Taipei Times",
      "url": "https://www.taipeitimes.com/News/editorials/archives/2026/04/26/2003856236",
      "published_date": "2026-04-26T00:00:00Z",
      "category": "Local Events"
    }
  ]
}