{
  "country": "taiwan",
  "last_updated": "2026-04-16T23:46:15Z",
  "stories": [
    {
      "title": "The KMT has stopped saying no to Beijing",
      "source": "Taipei Times",
      "url": "https://www.taipeitimes.com/News/editorials/archives/2026/04/17/2003855738",
      "published_date": "2026-04-17T00:00:00Z",
      "category": "Diplomacy"
    },
    {
      "title": "Trump’s Hormuz blockade risks showdown with China before Xi summit",
      "source": "Taipei Times",
      "url": "https://www.taipeitimes.com/News/editorials/archives/2026/04/17/2003855740",
      "published_date": "2026-04-17T00:00:00Z",
      "category": "Diplomacy"
    },
    {
      "title": "Warriors rally to eliminate Clippers",
      "source": "Taipei Times",
      "url": "https://www.taipeitimes.com/News/sport/archives/2026/04/17/2003855750",
      "published_date": "2026-04-17T00:00:00Z",
      "category": "Diplomacy"
    },
    {
      "title": "Tomomi Hanahara posted family photos but wore a hat the whole time! Fans worry: Not quite right",
      "source": "Liberty Times",
      "url": "https://ent.ltn.com.tw/news/breakingnews/5406598",
      "published_date": "2026-04-16T23:35:00Z",
      "category": "Diplomacy"
    },
    {
      "title": "MLB》\"Judge\"'s 8th home run king is useless! Yankees' $6.9 billion ace loses in worst game of season",
      "source": "Liberty Times",
      "url": "https://sports.ltn.com.tw/news/breakingnews/5406641",
      "published_date": "2026-04-16T23:32:56Z",
      "category": "Diplomacy"
    },
    {
      "title": "It’s a wave fist! \"Quick Fighting Tornado\" trailer reveals fist-pumping homage to the game",
      "source": "Liberty Times",
      "url": "https://ent.ltn.com.tw/news/breakingnews/5406617",
      "published_date": "2026-04-16T23:15:00Z",
      "category": "Diplomacy"
    },
    {
      "title": "Tom Cruise is sure to fly again! \"Defender 3\" is officially announced to be released",
      "source": "Liberty Times",
      "url": "https://ent.ltn.com.tw/news/breakingnews/5406620",
      "published_date": "2026-04-16T22:58:39Z",
      "category": "Diplomacy"
    },
    {
      "title": "absurd! An art teacher who measured a female student's breasts and found her breasts licked her breasts argued that she was suffering from cancer and couldn't get an erection even though she was taking medication",
      "source": "Liberty Times",
      "url": "https://news.ltn.com.tw/news/society/breakingnews/5406635",
      "published_date": "2026-04-16T22:54:11Z",
      "category": "Diplomacy"
    },
    {
      "title": "Chinese power bank pretends to be certified by Taiwan, online auctioneer sentenced for \"copying and pasting\"",
      "source": "Liberty Times",
      "url": "https://news.ltn.com.tw/news/society/breakingnews/5406619",
      "published_date": "2026-04-16T22:45:12Z",
      "category": "Diplomacy"
    },
    {
      "title": "Fii, a subsidiary of Hon Hai, has a strong outlook. Chairman Zheng Hongmeng: The company has entered the first year of CPO",
      "source": "Liberty Times",
      "url": "https://ec.ltn.com.tw/article/breakingnews/5406586",
      "published_date": "2026-04-16T22:27:39Z",
      "category": "Diplomacy"
    },
    {
      "title": "US-Iran ceasefire agreement planned to be extended, White House optimistically assesses second round of peace talks",
      "source": "Liberty Times",
      "url": "https://news.ltn.com.tw/news/world/breakingnews/5406527",
      "published_date": "2026-04-16T22:18:46Z",
      "category": "Diplomacy"
    },
    {
      "title": "Come in! Mazu's fire mowing in Baishatun was completed and she boarded the sedan chair in the early morning to start the 4-day return journey",
      "source": "Liberty Times",
      "url": "https://news.ltn.com.tw/news/life/breakingnews/5406610",
      "published_date": "2026-04-16T22:07:30Z",
      "category": "Diplomacy"
    },
    {
      "title": "Beijing’s push to “de-dollarize” is useless! Foreign holdings of U.S. debt hit record high in February",
      "source": "Liberty Times",
      "url": "https://ec.ltn.com.tw/article/breakingnews/5406532",
      "published_date": "2026-04-16T21:59:02Z",
      "category": "Diplomacy"
    },
    {
      "title": "TPASS funds are available for expenditure. Zhuo Kui: After the general budget is submitted to the committee, a letter is requested to be implemented by the agency.",
      "source": "Liberty Times",
      "url": "https://news.ltn.com.tw/news/politics/paper/1751205",
      "published_date": "2026-04-16T21:30:00Z",
      "category": "Diplomacy"
    },
    {
      "title": "National security source: Xi Zheng will advance the goal of \"disarmament of Taiwan\"",
      "source": "Liberty Times",
      "url": "https://news.ltn.com.tw/news/politics/paper/1751195",
      "published_date": "2026-04-16T21:30:00Z",
      "category": "Diplomacy"
    },
    {
      "title": "Zheng Liwen’s visit to China cost 4.8 million, and the whole people paid the bill. DPP: It violated the regulations of the Democracy Foundation and should refuse subsidies.",
      "source": "Liberty Times",
      "url": "https://news.ltn.com.tw/news/politics/paper/1751185",
      "published_date": "2026-04-16T21:30:00Z",
      "category": "Diplomacy"
    },
    {
      "title": "Introducing the latest version of the \"Taiwan Relations Strengthening Act\", U.S. Senate members urge Taiwan to strengthen its defense capabilities",
      "source": "Liberty Times",
      "url": "https://news.ltn.com.tw/news/politics/paper/1751200",
      "published_date": "2026-04-16T21:30:00Z",
      "category": "Diplomacy"
    },
    {
      "title": "Gu Li meets with Zhu Lilun to talk about Taiwan's resilience and security",
      "source": "Liberty Times",
      "url": "https://news.ltn.com.tw/news/politics/paper/1751201",
      "published_date": "2026-04-16T21:30:00Z",
      "category": "Diplomacy"
    },
    {
      "title": "Cathay Pacific CUBE Card adds \"Formosa Plastics Home\"",
      "source": "Liberty Times",
      "url": "https://ec.ltn.com.tw/article/paper/1751176",
      "published_date": "2026-04-16T21:30:00Z",
      "category": "Diplomacy"
    },
    {
      "title": "Ambassadors from thirty NATO countries visit Japan, rare in scale",
      "source": "Liberty Times",
      "url": "https://news.ltn.com.tw/news/world/paper/1751193",
      "published_date": "2026-04-16T21:30:00Z",
      "category": "Diplomacy"
    },
    {
      "title": "Ocean radar network plans outlined",
      "source": "Taipei Times",
      "url": "https://www.taipeitimes.com/News/front/archives/2026/04/17/2003855745",
      "published_date": "2026-04-17T00:00:00Z",
      "category": "Military"
    },
    {
      "title": "Progress on general budget continues",
      "source": "Taipei Times",
      "url": "https://www.taipeitimes.com/News/taiwan/archives/2026/04/17/2003855756",
      "published_date": "2026-04-17T00:00:00Z",
      "category": "Military"
    },
    {
      "title": "Urban resilience drills to be held with Han Kuang",
      "source": "Taipei Times",
      "url": "https://www.taipeitimes.com/News/taiwan/archives/2026/04/17/2003855757",
      "published_date": "2026-04-17T00:00:00Z",
      "category": "Military"
    },
    {
      "title": "Air force serviceman receives two year sentence",
      "source": "Taipei Times",
      "url": "https://www.taipeitimes.com/News/taiwan/archives/2026/04/17/2003855766",
      "published_date": "2026-04-17T00:00:00Z",
      "category": "Military"
    },
    {
      "title": "Australia to boost defense spending",
      "source": "Taipei Times",
      "url": "https://www.taipeitimes.com/News/world/archives/2026/04/17/2003855771",
      "published_date": "2026-04-17T00:00:00Z",
      "category": "Military"
    },
    {
      "title": "Ukraine’s mysterious “Cardia Legion” exposed! 30 volunteers transformed into 40,000 combat troops",
      "source": "Liberty Times",
      "url": "https://news.ltn.com.tw/news/world/breakingnews/5406622",
      "published_date": "2026-04-16T23:14:45Z",
      "category": "Military"
    },
    {
      "title": "WTT Branch Tournament\" Overthrown the former world No. 10 player and advanced to the top 4 Huang Yuxi said it was incredible",
      "source": "Liberty Times",
      "url": "https://sports.ltn.com.tw/news/breakingnews/5406621",
      "published_date": "2026-04-16T23:01:18Z",
      "category": "Military"
    },
    {
      "title": "Cross-party U.S. senators jointly send a letter to Han Kuo-yu to urge the passage of a special defense budget",
      "source": "Liberty Times",
      "url": "https://news.ltn.com.tw/news/politics/breakingnews/5406530",
      "published_date": "2026-04-16T22:20:25Z",
      "category": "Military"
    },
    {
      "title": "Holmes didn’t receive even 1 dime of the “toll”! Iran was dumbfounded",
      "source": "Liberty Times",
      "url": "https://ec.ltn.com.tw/article/breakingnews/5406543",
      "published_date": "2026-04-16T21:56:53Z",
      "category": "Military"
    },
    {
      "title": "When will the next round of negotiations between the United States and Iran take place? Trump hints it could be this weekend",
      "source": "Liberty Times",
      "url": "https://news.ltn.com.tw/news/world/breakingnews/5406628",
      "published_date": "2026-04-16T21:45:03Z",
      "category": "Military"
    },
    {
      "title": "Secretly photographed Patriot missile deployment map for 4,000 yuan, former air commander's acquittal reversed and sentence reduced to 2 years",
      "source": "Liberty Times",
      "url": "https://news.ltn.com.tw/news/politics/paper/1751206",
      "published_date": "2026-04-16T21:30:00Z",
      "category": "Military"
    },
    {
      "title": "Cheng Lai-wen's visit to China requires a 4.8 million treasury subsidy.\" Legislator approved: If the Democracy Foundation sponsors the Kuomintang, it is sponsoring the CCP's united front against Taiwan.",
      "source": "Liberty Times",
      "url": "https://news.ltn.com.tw/news/politics/paper/1751194",
      "published_date": "2026-04-16T21:30:00Z",
      "category": "Military"
    },
    {
      "title": "\"The End of Rumors\" Rumors spread online that \"the ban on 1.4 billion mainland tourists visiting Taiwan has been lifted\"? Taiwan Fact Checking Center: Fake news",
      "source": "Liberty Times",
      "url": "https://news.ltn.com.tw/news/politics/paper/1751207",
      "published_date": "2026-04-16T21:30:00Z",
      "category": "Military"
    },
    {
      "title": "The Kuomintang’s application for a subsidy of 4.8 million yuan “has not yet been written off”",
      "source": "Liberty Times",
      "url": "https://news.ltn.com.tw/news/politics/paper/1751196",
      "published_date": "2026-04-16T21:30:00Z",
      "category": "Military"
    },
    {
      "title": "Obtained bids for two UAVs from the Ministry of National Defense, Thunder Tiger will be shipped within one month",
      "source": "Liberty Times",
      "url": "https://ec.ltn.com.tw/article/paper/1751221",
      "published_date": "2026-04-16T21:30:00Z",
      "category": "Military"
    },
    {
      "title": "Financial Green Light》Why Japan and South Korea want migrant workers from India",
      "source": "Liberty Times",
      "url": "https://ec.ltn.com.tw/article/paper/1751225",
      "published_date": "2026-04-16T21:30:00Z",
      "category": "Military"
    },
    {
      "title": "Uzbek army’s new combat model regains large areas of Wunan territory",
      "source": "Liberty Times",
      "url": "https://news.ltn.com.tw/news/world/paper/1751189",
      "published_date": "2026-04-16T21:30:00Z",
      "category": "Military"
    },
    {
      "title": "中英對照讀新聞》Dutch Queen Joins Armed Forces in Symbolic Move of Support for Military 荷蘭王后加入武裝部隊 支持軍方的象徵之舉",
      "source": "Liberty Times",
      "url": "https://news.ltn.com.tw/news/world/paper/1751232",
      "published_date": "2026-04-16T21:30:00Z",
      "category": "Military"
    },
    {
      "title": "Arsenal of Democracy! The Pentagon expands weapons production and seeks out domestic automakers",
      "source": "Liberty Times",
      "url": "https://news.ltn.com.tw/news/world/paper/1751192",
      "published_date": "2026-04-16T21:30:00Z",
      "category": "Military"
    },
    {
      "title": "The United States is optimistic about the second round of negotiations and will simultaneously deploy reinforcements to the Middle East",
      "source": "Liberty Times",
      "url": "https://news.ltn.com.tw/news/world/paper/1751191",
      "published_date": "2026-04-16T21:30:00Z",
      "category": "Military"
    },
    {
      "title": "More grid resilience, not capabilities needed",
      "source": "Taipei Times",
      "url": "https://www.taipeitimes.com/News/taiwan/archives/2026/04/17/2003855762",
      "published_date": "2026-04-17T00:00:00Z",
      "category": "Energy"
    },
    {
      "title": "Taiwan closely monitoring oil shipments, minister says",
      "source": "Taipei Times",
      "url": "https://www.taipeitimes.com/News/biz/archives/2026/04/17/2003855731",
      "published_date": "2026-04-17T00:00:00Z",
      "category": "Energy"
    },
    {
      "title": "The energy beneath Taiwan’s feet",
      "source": "Taipei Times",
      "url": "https://www.taipeitimes.com/News/feat/archives/2026/04/17/2003855742",
      "published_date": "2026-04-17T00:00:00Z",
      "category": "Energy"
    },
    {
      "title": "How to receive Guyu Caishui? View the 12 zodiac signs \"positive wealth, partial wealth, and leakage wealth\" at once",
      "source": "Liberty Times",
      "url": "https://ent.ltn.com.tw/news/breakingnews/5406589",
      "published_date": "2026-04-16T21:55:00Z",
      "category": "Energy"
    },
    {
      "title": "The proportion of green electricity meets the standard. Manager: It can meet the RE100 demand of enterprises.",
      "source": "Liberty Times",
      "url": "https://ec.ltn.com.tw/article/paper/1751175",
      "published_date": "2026-04-16T21:30:00Z",
      "category": "Energy"
    },
    {
      "title": "The market doubts whether the US-Iran peace talks can resolve supply problems; international oil prices rise",
      "source": "Liberty Times",
      "url": "https://ec.ltn.com.tw/article/breakingnews/5406625",
      "published_date": "2026-04-16T20:00:05Z",
      "category": "Energy"
    },
    {
      "title": "\"Text spoilers\" can also be considered copyright infringement. The Tokyo District Court found the person in charge of the website guilty.",
      "source": "Liberty Times",
      "url": "https://news.ltn.com.tw/news/world/breakingnews/5406418",
      "published_date": "2026-04-16T12:33:14Z",
      "category": "Energy"
    },
    {
      "title": "Crude oil reaches a sky-high price of US$286 per barrel, and it is rumored that \"this country in Asia\" swallowed it in tears",
      "source": "Liberty Times",
      "url": "https://ec.ltn.com.tw/article/breakingnews/5406378",
      "published_date": "2026-04-16T11:40:24Z",
      "category": "Energy"
    },
    {
      "title": "Divorced and together for 25 years? Tom Cruise and Nicole Kidman appeared at the same venue, and the whole network was watching closely",
      "source": "Liberty Times",
      "url": "https://ent.ltn.com.tw/news/breakingnews/5406412",
      "published_date": "2026-04-16T11:27:00Z",
      "category": "Energy"
    },
    {
      "title": "The Bureau of Water Management asked Taipower to refuse the water consumption contract, but the contract can be terminated and transferred to private green electricity.",
      "source": "Liberty Times",
      "url": "https://ec.ltn.com.tw/article/breakingnews/5406368",
      "published_date": "2026-04-16T10:53:34Z",
      "category": "Energy"
    },
    {
      "title": "Iran says major differences in US-Iran talks remain, and mediator \"Trump's favorite marshal\" has a long way to go",
      "source": "Liberty Times",
      "url": "https://news.ltn.com.tw/news/world/breakingnews/5406191",
      "published_date": "2026-04-16T09:00:57Z",
      "category": "Energy"
    },
    {
      "title": "Oil prices likely permanently affected: official",
      "source": "Taipei Times",
      "url": "https://www.taipeitimes.com/News/biz/archives/2026/04/16/2003855666",
      "published_date": "2026-04-16T00:00:00Z",
      "category": "Energy"
    },
    {
      "title": "ASML raises 2026 sales forecast as AI demand fuels growth",
      "source": "Taipei Times",
      "url": "https://www.taipeitimes.com/News/biz/archives/2026/04/16/2003855670",
      "published_date": "2026-04-16T00:00:00Z",
      "category": "Energy"
    },
    {
      "title": "Total ban! U.S. Treasury Secretary warns 2 Chinese banks that \"subordinate sanctions will be imposed on Iranian funds\"",
      "source": "Liberty Times",
      "url": "https://ec.ltn.com.tw/article/breakingnews/5405348",
      "published_date": "2026-04-15T23:28:09Z",
      "category": "Energy"
    },
    {
      "title": "Total ban! U.S. Treasury Secretary warns 2 Chinese banks that \"funds related to Iran may be subject to secondary sanctions\"",
      "source": "Liberty Times",
      "url": "https://news.ltn.com.tw/news/world/breakingnews/5405348",
      "published_date": "2026-04-15T23:28:09Z",
      "category": "Energy"
    },
    {
      "title": "Taipower is trying to calm the price wave: The government owes 200 billion in electricity bills",
      "source": "Liberty Times",
      "url": "https://ec.ltn.com.tw/article/paper/1751042",
      "published_date": "2026-04-15T21:30:00Z",
      "category": "Energy"
    },
    {
      "title": "Taking advantage of the Iran war to stock up on oil, Bessant’s approval is unreliable",
      "source": "Liberty Times",
      "url": "https://ec.ltn.com.tw/article/paper/1751039",
      "published_date": "2026-04-15T21:30:00Z",
      "category": "Energy"
    },
    {
      "title": "Japan helps Southeast Asia purchase crude oil to stabilize supply chain",
      "source": "Liberty Times",
      "url": "https://news.ltn.com.tw/news/world/paper/1751068",
      "published_date": "2026-04-15T21:30:00Z",
      "category": "Energy"
    },
    {
      "title": "The market assesses the prospects of war in the Middle East; European stocks have divergent trends",
      "source": "Liberty Times",
      "url": "https://ec.ltn.com.tw/article/breakingnews/5405316",
      "published_date": "2026-04-15T16:48:03Z",
      "category": "Energy"
    },
    {
      "title": "Yilan was shocked to see a \"public toilet\" locked with an iron door. He was bitter: To prevent tourists from having their urine and urine stolen?",
      "source": "Liberty Times",
      "url": "https://news.ltn.com.tw/news/politics/breakingnews/5405289",
      "published_date": "2026-04-15T16:38:30Z",
      "category": "Energy"
    },
    {
      "title": "Taiwan’s market cap tops US$4 trillion",
      "source": "Taipei Times",
      "url": "https://www.taipeitimes.com/News/front/archives/2026/04/17/2003855747",
      "published_date": "2026-04-17T00:00:00Z",
      "category": "Economy"
    },
    {
      "title": "TSMC projects over 30% sales growth",
      "source": "Taipei Times",
      "url": "https://www.taipeitimes.com/News/biz/archives/2026/04/17/2003855728",
      "published_date": "2026-04-17T00:00:00Z",
      "category": "Economy"
    },
    {
      "title": "Abandoning humanitarian aid, the U.S.’s declaration of “trade over aid” may trigger a backlash",
      "source": "Liberty Times",
      "url": "https://news.ltn.com.tw/news/world/breakingnews/5406616",
      "published_date": "2026-04-16T23:29:11Z",
      "category": "Economy"
    },
    {
      "title": "LTN Economic Express》10 yuan per pack Indonesian products are sweeping across Africa",
      "source": "Liberty Times",
      "url": "https://ec.ltn.com.tw/article/breakingnews/5392170",
      "published_date": "2026-04-16T23:00:00Z",
      "category": "Economy"
    },
    {
      "title": "\"Housekeeping for retirement\" can be realized! Taiwan Financial Union joins hands with Huayin to integrate chartered custody and activate pension funds",
      "source": "Liberty Times",
      "url": "https://estate.ltn.com.tw/article/27537",
      "published_date": "2026-04-16T22:30:00Z",
      "category": "Economy"
    },
    {
      "title": "Daily salary exceeds 80 million! Wei Zhejia’s annual salary jumped to 2.422 billion yuan last year",
      "source": "Liberty Times",
      "url": "https://ec.ltn.com.tw/article/breakingnews/5406600",
      "published_date": "2026-04-16T22:00:00Z",
      "category": "Economy"
    },
    {
      "title": "U.S. stocks close》TSMC ADR drops more than 3%! S&P and Nasdaq continue to reach new highs",
      "source": "Liberty Times",
      "url": "https://ec.ltn.com.tw/article/breakingnews/5406630",
      "published_date": "2026-04-16T21:56:11Z",
      "category": "Economy"
    },
    {
      "title": "The market is optimistic about the Middle East war; U.S. stocks close in red, S&P Nasdaq hits new high",
      "source": "Liberty Times",
      "url": "https://ec.ltn.com.tw/article/breakingnews/5406629",
      "published_date": "2026-04-16T21:45:04Z",
      "category": "Economy"
    },
    {
      "title": "The Democracy Foundation is listed as a \"Taiwan independence organization\" by China and banned from dealing with it",
      "source": "Liberty Times",
      "url": "https://news.ltn.com.tw/news/politics/paper/1751197",
      "published_date": "2026-04-16T21:30:00Z",
      "category": "Economy"
    },
    {
      "title": "Hot Stocks》Rumors about OEM memory, UMC surges to daily limit",
      "source": "Liberty Times",
      "url": "https://ec.ltn.com.tw/article/paper/1751222",
      "published_date": "2026-04-16T21:30:00Z",
      "category": "Economy"
    },
    {
      "title": "Musk seeks cooperation with Intel Wei Zhejia: There are no shortcuts in wafer foundry",
      "source": "Liberty Times",
      "url": "https://ec.ltn.com.tw/article/paper/1751179",
      "published_date": "2026-04-16T21:30:00Z",
      "category": "Economy"
    },
    {
      "title": "Hot Stocks》Three major legal persons swept the goods, Qiangmao led to a surge in sales",
      "source": "Liberty Times",
      "url": "https://ec.ltn.com.tw/article/paper/1751223",
      "published_date": "2026-04-16T21:30:00Z",
      "category": "Economy"
    },
    {
      "title": "Market situation analysis》Short-term deviation is too large, pay attention to pullback if the price rises",
      "source": "Liberty Times",
      "url": "https://ec.ltn.com.tw/article/paper/1751224",
      "published_date": "2026-04-16T21:30:00Z",
      "category": "Economy"
    },
    {
      "title": "TSMC breaks record Q1, outlook for this year fully revised",
      "source": "Liberty Times",
      "url": "https://ec.ltn.com.tw/article/paper/1751178",
      "published_date": "2026-04-16T21:30:00Z",
      "category": "Economy"
    },
    {
      "title": "Taiwan stock market value exceeds US$4.1 trillion, surpassing British stocks for the first time",
      "source": "Liberty Times",
      "url": "https://ec.ltn.com.tw/article/paper/1751180",
      "published_date": "2026-04-16T21:30:00Z",
      "category": "Economy"
    },
    {
      "title": "Going westward, Q1’s investment in China accounts for less than 1%",
      "source": "Liberty Times",
      "url": "https://ec.ltn.com.tw/article/paper/1751181",
      "published_date": "2026-04-16T21:30:00Z",
      "category": "Economy"
    },
    {
      "title": "The market is optimistic about the development of the situation in the Middle East; European stocks closed higher",
      "source": "Liberty Times",
      "url": "https://ec.ltn.com.tw/article/breakingnews/5406613",
      "published_date": "2026-04-16T17:21:04Z",
      "category": "Economy"
    },
    {
      "title": "Investment Credit: AI spillover effects are fermenting, and exports are expected to be strong in the second quarter",
      "source": "Liberty Times",
      "url": "https://ec.ltn.com.tw/article/breakingnews/5406526",
      "published_date": "2026-04-16T13:54:43Z",
      "category": "Economy"
    },
    {
      "title": "Li Yujia of the Federation of Small and Medium Enterprises was awarded the Economic Professional Medal",
      "source": "Liberty Times",
      "url": "https://ec.ltn.com.tw/article/breakingnews/5406515",
      "published_date": "2026-04-16T13:46:34Z",
      "category": "Economy"
    },
    {
      "title": "The total premium income of the life insurance industry in the first quarter was nearly 800 billion, and the investment-type first-year premium increased by more than 50% year-on-year.",
      "source": "Liberty Times",
      "url": "https://ec.ltn.com.tw/article/breakingnews/5406509",
      "published_date": "2026-04-16T13:39:51Z",
      "category": "Economy"
    },
    {
      "title": "Parties debate KMT chair’s China trip funding",
      "source": "Taipei Times",
      "url": "https://www.taipeitimes.com/News/front/archives/2026/04/17/2003855746",
      "published_date": "2026-04-17T00:00:00Z",
      "category": "Local Events"
    },
    {
      "title": "Blaze tears through Australian refinery; disruptions feared",
      "source": "Taipei Times",
      "url": "https://www.taipeitimes.com/News/front/archives/2026/04/17/2003855748",
      "published_date": "2026-04-17T00:00:00Z",
      "category": "Local Events"
    },
    {
      "title": "Russian strikes kill 16 in Ukraine",
      "source": "Taipei Times",
      "url": "https://www.taipeitimes.com/News/front/archives/2026/04/17/2003855749",
      "published_date": "2026-04-17T00:00:00Z",
      "category": "Local Events"
    },
    {
      "title": "Council to assess China’s call for direct flight routes",
      "source": "Taipei Times",
      "url": "https://www.taipeitimes.com/News/taiwan/archives/2026/04/17/2003855758",
      "published_date": "2026-04-17T00:00:00Z",
      "category": "Local Events"
    },
    {
      "title": "Hsinchu mayor Kao plagiarism case remanded to district court for retrial",
      "source": "Taipei Times",
      "url": "https://www.taipeitimes.com/News/taiwan/archives/2026/04/17/2003855759",
      "published_date": "2026-04-17T00:00:00Z",
      "category": "Local Events"
    },
    {
      "title": "NSB head visits Eswatini ahead of presidential trip",
      "source": "Taipei Times",
      "url": "https://www.taipeitimes.com/News/taiwan/archives/2026/04/17/2003855760",
      "published_date": "2026-04-17T00:00:00Z",
      "category": "Local Events"
    },
    {
      "title": "US senators introduce updated bill supporting Taiwan",
      "source": "Taipei Times",
      "url": "https://www.taipeitimes.com/News/taiwan/archives/2026/04/17/2003855761",
      "published_date": "2026-04-17T00:00:00Z",
      "category": "Local Events"
    },
    {
      "title": "Biologists urge change to marine conservation policy",
      "source": "Taipei Times",
      "url": "https://www.taipeitimes.com/News/taiwan/archives/2026/04/17/2003855763",
      "published_date": "2026-04-17T00:00:00Z",
      "category": "Local Events"
    },
    {
      "title": "Train services added for Dajia Matsu pilgrimage",
      "source": "Taipei Times",
      "url": "https://www.taipeitimes.com/News/taiwan/archives/2026/04/17/2003855764",
      "published_date": "2026-04-17T00:00:00Z",
      "category": "Local Events"
    },
    {
      "title": "Local farms win grand awards for agritourism",
      "source": "Taipei Times",
      "url": "https://www.taipeitimes.com/News/taiwan/archives/2026/04/17/2003855765",
      "published_date": "2026-04-17T00:00:00Z",
      "category": "Local Events"
    },
    {
      "title": "Taiwan News Quick Take",
      "source": "Taipei Times",
      "url": "https://www.taipeitimes.com/News/taiwan/archives/2026/04/17/2003855767",
      "published_date": "2026-04-17T00:00:00Z",
      "category": "Local Events"
    },
    {
      "title": "Dome experience",
      "source": "Taipei Times",
      "url": "https://www.taipeitimes.com/News/taiwan/archives/2026/04/17/2003855768",
      "published_date": "2026-04-17T00:00:00Z",
      "category": "Local Events"
    },
    {
      "title": "Manga fever",
      "source": "Taipei Times",
      "url": "https://www.taipeitimes.com/News/taiwan/archives/2026/04/17/2003855769",
      "published_date": "2026-04-17T00:00:00Z",
      "category": "Local Events"
    },
    {
      "title": "Artistry showcase",
      "source": "Taipei Times",
      "url": "https://www.taipeitimes.com/News/taiwan/archives/2026/04/17/2003855770",
      "published_date": "2026-04-17T00:00:00Z",
      "category": "Local Events"
    },
    {
      "title": "Largan reports better margins",
      "source": "Taipei Times",
      "url": "https://www.taipeitimes.com/News/biz/archives/2026/04/17/2003855729",
      "published_date": "2026-04-17T00:00:00Z",
      "category": "Local Events"
    },
    {
      "title": "Taiwanese employers recruiting more foreign talent",
      "source": "Taipei Times",
      "url": "https://www.taipeitimes.com/News/biz/archives/2026/04/17/2003855730",
      "published_date": "2026-04-17T00:00:00Z",
      "category": "Local Events"
    },
    {
      "title": "Life insurance premium income rose 18.6% in Q1",
      "source": "Taipei Times",
      "url": "https://www.taipeitimes.com/News/biz/archives/2026/04/17/2003855732",
      "published_date": "2026-04-17T00:00:00Z",
      "category": "Local Events"
    },
    {
      "title": "Musk asks suppliers to move at ‘light speed’ on Terafab project",
      "source": "Taipei Times",
      "url": "https://www.taipeitimes.com/News/biz/archives/2026/04/17/2003855733",
      "published_date": "2026-04-17T00:00:00Z",
      "category": "Local Events"
    },
    {
      "title": "Slowing sales",
      "source": "Taipei Times",
      "url": "https://www.taipeitimes.com/News/biz/archives/2026/04/17/2003855734",
      "published_date": "2026-04-17T00:00:00Z",
      "category": "Local Events"
    },
    {
      "title": "EDITORIAL Taiwan must resist China’s pressure",
      "source": "Taipei Times",
      "url": "https://www.taipeitimes.com/News/editorials/archives/2026/04/17/2003855735",
      "published_date": "2026-04-17T00:00:00Z",
      "category": "Local Events"
    }
  ]
}